MANIFEST.in
readme.rst
requirements.txt
sample.conf
setup.cfg
setup.py
yact/__init__.py
yact/config.py
yact.egg-info/PKG-INFO
yact.egg-info/SOURCES.txt
yact.egg-info/dependency_links.txt
yact.egg-info/requires.txt
yact.egg-info/top_level.txt