Metadata-Version: 1.1
Name: yact
Version: 0.5.1
Summary: Yet Another Config Tool
Home-page: https://github.com/dreadpirate15/yact
Author: Jesse Roberts
Author-email: jesse@hackedpotatoes.com
License: MIT
Keywords: yaml yact settings config parser configuration
Platform: UNKNOWN
Classifier: Natural Language :: English
Classifier: Development Status :: 4 - Beta
Classifier: Intended Audience :: Developers
Classifier: License :: OSI Approved :: MIT License
Classifier: Programming Language :: Python :: 2
Classifier: Programming Language :: Python :: 2.7
Classifier: Programming Language :: Python :: 3
Classifier: Programming Language :: Python :: 3.3
Classifier: Programming Language :: Python :: 3.4
Classifier: Programming Language :: Python :: 3.5
